CHANGES
LICENSE
MANIFEST.in
README
setup.cfg
setup.py
test_cache.py
test_template.html
Flask_Cache_Latest.egg-info/PKG-INFO
Flask_Cache_Latest.egg-info/SOURCES.txt
Flask_Cache_Latest.egg-info/dependency_links.txt
Flask_Cache_Latest.egg-info/not-zip-safe
Flask_Cache_Latest.egg-info/requires.txt
Flask_Cache_Latest.egg-info/top_level.txt
docs/Makefile
docs/conf.py
docs/index.rst
docs/make.bat
docs/_static/flask-cache.png
docs/_themes/README
docs/_themes/flask_theme_support.py
docs/_themes/flask/theme.conf
docs/_themes/flask/static/flasky.css_t
docs/_themes/flask_small/layout.html
docs/_themes/flask_small/theme.conf
docs/_themes/flask_small/static/flasky.css_t
flask_cache/__init__.py
flask_cache/_compat.py
flask_cache/backends.py
flask_cache/jinja2ext.py